zbench/__init__.py
zbench/__main__.py
zbench/formatters.py
zbench/impl.py
zbench/util.py
zbench-0.1.0.dist-info/METADATA
zbench-0.1.0.dist-info/WHEEL
zbench-0.1.0.dist-info/entry_points.txt
zbench-0.1.0.dist-info/top_level.txt
zbench-0.1.0.dist-info/RECORD
