Metadata-Version: 2.1
Name: zbench
Version: 0.1.0
Summary: Compression benchmarks
Home-page: https://github.com/chbrown/zbench
Author: Christopher Brown
Author-email: io@henrian.com
License: MIT
Platform: UNKNOWN
Classifier: Environment :: Console
Classifier: Intended Audience :: Developers
Classifier: License :: OSI Approved :: MIT License
Classifier: Programming Language :: Python
Classifier: Topic :: System :: Archiving
Classifier: Topic :: System :: Archiving :: Backup
Requires-Python: >=3.6
Requires-Dist: click (>=7.0)
